LICENSE
MANIFEST.in
README.md
setup.py
revelionn/__init__.py
revelionn/activation_extraction.py
revelionn/concept_extraction.py
revelionn/datasets.py
revelionn/early_stopping.py
revelionn/main_module.py
revelionn/mapping_module.py
revelionn/mapping_trainer.py
revelionn/occlusion.py
revelionn.egg-info/PKG-INFO
revelionn.egg-info/SOURCES.txt
revelionn.egg-info/dependency_links.txt
revelionn.egg-info/requires.txt
revelionn.egg-info/top_level.txt
revelionn/mapping_nets/__init__.py
revelionn/mapping_nets/simultaneous_mapping_net.py
revelionn/mapping_nets/single_mapping_net.py
revelionn/utils/__init__.py
revelionn/utils/explanation.py
revelionn/utils/model.py
revelionn/utils/onto_justify.jar