Metadata-Version: 2.1
Name: revelionn
Version: 1.0.2
Summary: Retrospective Extraction of Visual and Logical Insights for Ontology-based interpretation of Neural Networks
Home-page: https://github.com/cais-lab/revelionn
Author: CAIS Lab
Author-email: agafonov.a@spcras.ru
License: BSD 3-Clause
Keywords: explainable AI,XAI,interpretation,black-box,convolutional neural network,ontology,concept extraction,visual explanation,logical explanation
Classifier: License :: OSI Approved :: BSD License
Classifier: Programming Language :: Python :: 3.9
Classifier: Programming Language :: Python :: 3.10
Classifier: Programming Language :: Python :: 3.11
Requires-Python: >=3.9
License-File: LICENSE
